pattern_causality/__init__.py
pattern_causality/databank.cpp
pattern_causality/datasets.py
pattern_causality/distancematrix.cpp
pattern_causality/fcp.cpp
pattern_causality/fillPCMatrix.cpp
pattern_causality/natureOfCausality.cpp
pattern_causality/pastNNs.cpp
pattern_causality/pattern_causality.py
pattern_causality/patternhashing.cpp
pattern_causality/patternspace.cpp
pattern_causality/predictionY.cpp
pattern_causality/projectedNNs.cpp
pattern_causality/signaturespace.cpp
pattern_causality/statespace.cpp
pattern_causality/data/Climate_Indices.csv
utils/databank.cpython-39-darwin.so
utils/distancematrix.cpython-39-darwin.so
utils/fcp.cpython-39-darwin.so
utils/fillPCMatrix.cpython-39-darwin.so
utils/natureOfCausality.cpython-39-darwin.so
utils/pastNNs.cpython-39-darwin.so
utils/patternhashing.cpython-39-darwin.so
utils/patternspace.cpython-39-darwin.so
utils/predictionY.cpython-39-darwin.so
utils/projectedNNs.cpython-39-darwin.so
utils/signaturespace.cpython-39-darwin.so
utils/statespace.cpython-39-darwin.so
pattern_causality-0.0.3.dist-info/LICENSE
pattern_causality-0.0.3.dist-info/METADATA
pattern_causality-0.0.3.dist-info/WHEEL
pattern_causality-0.0.3.dist-info/top_level.txt
pattern_causality-0.0.3.dist-info/RECORD
