Metadata-Version: 2.1
Name: pattern-causality
Version: 0.0.3
Summary: Pattern Causality Algorithm in Python
Home-page: https://github.com/skstavroglou/pattern_causality_py
Author: Stavros Stavroglou, Athanasios Pantelous, Hui Wang
Author-email: Stavros Stavroglou <stavros.k.stavroglou@gmail.com>, Athanasios Pantelous <Athanasios.Pantelous@monash.edu>, Hui Wang <huiw1128@gmail.com>
Maintainer: Hui Wang
Maintainer-email: Hui Wang <huiw1128@gmail.com>
License: BSD License
Project-URL: Homepage, https://github.com/skstavroglou/pattern_causality_py
Project-URL: Repository, https://github.com/skstavroglou/pattern_causality_py.git
Project-URL: Documentation, https://github.com/skstavroglou/pattern_causality_py#readme
Platform: all
Classifier: Programming Language :: Python :: 3
Classifier: Programming Language :: Python :: 3.8
Classifier: Programming Language :: Python :: 3.9
Classifier: Programming Language :: Python :: 3.10
Classifier: Programming Language :: Python :: 3.11
Requires-Python: >=3.8
License-File: LICENSE
Requires-Dist: numpy>=1.19.0
Requires-Dist: pandas>=1.0.0
Provides-Extra: dev
Requires-Dist: pytest>=6.0; extra == "dev"
Requires-Dist: pytest-cov>=2.0; extra == "dev"
Requires-Dist: black>=22.0; extra == "dev"
Requires-Dist: isort>=5.0; extra == "dev"
Requires-Dist: flake8>=4.0; extra == "dev"
